pygression/__init__.py
pygression/chord.py
pygression/consts.py
pygression/note.py
pygression/progression.py
pygression/roman.py
pygression/romanchord.py
pygression/utils.py
pygression/modifier/__init__.py
pygression/modifier/add.py
pygression/modifier/alter.py
pygression/modifier/base.py
pygression/modifier/no.py
pygression/modifier/sus.py
pygression/quality/__init__.py
pygression/quality/base.py
pygression/quality/extended.py
pygression/quality/seventh.py
pygression/quality/triad.py
pygression-1.0.0.dist-info/LICENSE
pygression-1.0.0.dist-info/METADATA
pygression-1.0.0.dist-info/WHEEL
pygression-1.0.0.dist-info/top_level.txt
pygression-1.0.0.dist-info/RECORD
