Metadata-Version: 2.2
Name: pygression
Version: 1.0.0
Summary: A package about chord progressions.
License-File: LICENSE
